DatasetsML/__init__.py
DatasetsML/main.py
DatasetsML-0.3.0.dist-info/METADATA
DatasetsML-0.3.0.dist-info/WHEEL
DatasetsML-0.3.0.dist-info/top_level.txt
DatasetsML-0.3.0.dist-info/RECORD
