Metadata-Version: 2.1
Name: DatasetsML
Version: 0.3.0
Summary: Datasets for ML models
Home-page: https://github.com/yourusername/my_package
Author: Schneider
Author-email: your.email@example.com
Classifier: Programming Language :: Python :: 3
Classifier: License :: OSI Approved :: MIT License
Classifier: Operating System :: OS Independent
Requires-Python: >=3.6
Requires-Dist: pgmpy
